Workbook

Sheet Start Here
A1: 📘 FINANCIAL MODEL
A2: 3-Statement model · DCF Valuation · Scenario Engine · Sensitivity Analysis
A4: Sheet | C4: What it does
A5: 1. Control Panel | C5: Set assumptions (yellow cells) and pick a scenario from the dropdown. All sheets update.
A6: 2. P&L | C6: Revenue → Gross Profit → EBITDA → Net Income across all forecast years.
A7: 3. Balance Sheet | C7: Assets = Liabilities + Equity every year. Green balance check = model is correct.
A8: 4. Cash Flow | C8: Indirect method: Net Income reconciled to ending cash. Ties back to Balance Sheet.
A9: 5. Valuation | C9: Unlevered FCFF DCF → Terminal Value → Enterprise Value → Equity Value. Multiples shown.
A10: 6. Sensitivity | C10: Data Table: vary Revenue Growth × COGS % to stress-test Year 5 Net Income.
A11: 7. Insights | C11: KPIs — margins, CAGR, break-even year, cash runway, balance & reconciliation checks.
A12: 8. Dashboard | C12: Charts: Revenue, Net Income, EBITDA Margin across all forecast years.
A14: Color coding
A15: Blue text on yellow | C15: Hardcoded input — safe to change
A16: Black text | C16: Formula — do not edit
A17: Green text | C17: Cross-sheet link — do not edit
A19: Sensitivity note | C19: After opening, go to Sensitivity sheet, select B3:H10, Data → What-If Analysis → Data Table. Row input = Control Panel B24, Col input = Control Panel B25.
A21: Version | C21: 4.0
A22: Author | C22: Abdallah
A23: Date | C23: 2026

Sheet Control Panel
A1: FINANCIAL MODEL – CONTROL PANEL
A2: Assumption | B2: Value | C2: Flag
A3: R&D % of Revenue | B3: 0.12 | C3: =IF($B$3>0.20,"⚠ R&D > 20% is very high","")
A4: SG&A % of Revenue | B4: 0.15 | C4: =IF($B$4>0.30,"⚠ SG&A > 30% — watch opex","")
A5: Tax Rate | B5: 0.21 | C5: =IF($B$5>0.35,"⚠ Tax rate above 35%","")
A6: Depreciation Rate (PP&E) | B6: 0.1 | C6: =IF($B$6>0.20,"⚠ Very rapid depreciation","")
A7: Capex % of Revenue | B7: 0.05 | C7: =IF($B$7>0.15,"⚠ Capex > 15% of revenue","")
A8: DSO (days) | B8: 45
A9: DIO (days) | B9: 60
A10: DPO (days) | B10: 30
A11: Interest Rate on Debt | B11: 0.05 | C11: =IF($B$11>0.10,"⚠ Interest rate above 10%","")
A12: Annual Debt Repayment | B12: 0
A13: WACC | B13: 0.09 | C13: =IF($B$13>0.15,"⚠ WACC > 15% is very high","")
A14: Perpetual Growth Rate | B14: 0.025 | C14: =IF($B$14>=$B$13,"⚠ g ≥ WACC → Terminal Value invalid","")
A17: Scenario | B17: Revenue Growth | C17: COGS %
A18: Base | B18: 0.1 | C18: 0.45 | D18: =IF($B$23=$A$18,"◀ active","")
A19: Best | B19: 0.18 | C19: 0.4 | D19: =IF($B$23=$A$19,"◀ active","")
A20: Worst | B20: 0.04 | C20: 0.55 | D20: =IF($B$23=$A$20,"◀ active","")
A23: ▶ Active Scenario | B23: Base
A24: Effective Revenue Growth | B24: =INDEX($B$18:$B$20,MATCH($B$23,$A$18:$A$20,0))
A25: Effective COGS % | B25: =INDEX($C$18:$C$20,MATCH($B$23,$A$18:$A$20,0))
A27: Model Health | B27: =IF(ABS(SUM('Balance Sheet'!$B$14:$F$14))<1,"✅ HEALTHY","❌ BALANCE ERROR")

Sheet P&L
A1: Line Item (USD) | B1: Year 1 | C1: Year 2 | D1: Year 3 | E1: Year 4 | F1: Year 5
A2: Revenue | B2: 1000000 | C2: ='P&L'!$B$2*(1+'Control Panel'!$B$24) | D2: ='P&L'!$C$2*(1+'Control Panel'!$B$24) | E2: ='P&L'!$D$2*(1+'Control Panel'!$B$24) | F2: ='P&L'!$E$2*(1+'Control Panel'!$B$24)
A3: Cost of Goods Sold | B3: ='P&L'!$B$2*'Control Panel'!$B$25 | C3: ='P&L'!$C$2*'Control Panel'!$B$25 | D3: ='P&L'!$D$2*'Control Panel'!$B$25 | E3: ='P&L'!$E$2*'Control Panel'!$B$25 | F3: ='P&L'!$F$2*'Control Panel'!$B$25
A4: Gross Profit | B4: ='P&L'!$B$2-'P&L'!$B$3 | C4: ='P&L'!$C$2-'P&L'!$C$3 | D4: ='P&L'!$D$2-'P&L'!$D$3 | E4: ='P&L'!$E$2-'P&L'!$E$3 | F4: ='P&L'!$F$2-'P&L'!$F$3
A5: R&D Expense | B5: ='P&L'!$B$2*'Control Panel'!$B$3 | C5: ='P&L'!$C$2*'Control Panel'!$B$3 | D5: ='P&L'!$D$2*'Control Panel'!$B$3 | E5: ='P&L'!$E$2*'Control Panel'!$B$3 | F5: ='P&L'!$F$2*'Control Panel'!$B$3
A6: SG&A Expense | B6: ='P&L'!$B$2*'Control Panel'!$B$4 | C6: ='P&L'!$C$2*'Control Panel'!$B$4 | D6: ='P&L'!$D$2*'Control Panel'!$B$4 | E6: ='P&L'!$E$2*'Control Panel'!$B$4 | F6: ='P&L'!$F$2*'Control Panel'!$B$4
A7: EBITDA | B7: ='P&L'!$B$4-'P&L'!$B$5-'P&L'!$B$6 | C7: ='P&L'!$C$4-'P&L'!$C$5-'P&L'!$C$6 | D7: ='P&L'!$D$4-'P&L'!$D$5-'P&L'!$D$6 | E7: ='P&L'!$E$4-'P&L'!$E$5-'P&L'!$E$6 | F7: ='P&L'!$F$4-'P&L'!$F$5-'P&L'!$F$6
A8: Depreciation & Amortization | B8: =500000*'Control Panel'!$B$6 | C8: ='Balance Sheet'!$B$5*'Control Panel'!$B$6 | D8: ='Balance Sheet'!$C$5*'Control Panel'!$B$6 | E8: ='Balance Sheet'!$D$5*'Control Panel'!$B$6 | F8: ='Balance Sheet'!$E$5*'Control Panel'!$B$6
A9: EBIT | B9: ='P&L'!$B$7-'P&L'!$B$8 | C9: ='P&L'!$C$7-'P&L'!$C$8 | D9: ='P&L'!$D$7-'P&L'!$D$8 | E9: ='P&L'!$E$7-'P&L'!$E$8 | F9: ='P&L'!$F$7-'P&L'!$F$8
A10: Interest Expense | B10: =200000*'Control Panel'!$B$11 | C10: ='Balance Sheet'!$B$9*'Control Panel'!$B$11 | D10: ='Balance Sheet'!$C$9*'Control Panel'!$B$11 | E10: ='Balance Sheet'!$D$9*'Control Panel'!$B$11 | F10: ='Balance Sheet'!$E$9*'Control Panel'!$B$11
A11: EBT | B11: ='P&L'!$B$9-'P&L'!$B$10 | C11: ='P&L'!$C$9-'P&L'!$C$10 | D11: ='P&L'!$D$9-'P&L'!$D$10 | E11: ='P&L'!$E$9-'P&L'!$E$10 | F11: ='P&L'!$F$9-'P&L'!$F$10
A12: Income Taxes | B12: =MAX('P&L'!$B$11*'Control Panel'!$B$5,0) | C12: =MAX('P&L'!$C$11*'Control Panel'!$B$5,0) | D12: =MAX('P&L'!$D$11*'Control Panel'!$B$5,0) | E12: =MAX('P&L'!$E$11*'Control Panel'!$B$5,0) | F12: =MAX('P&L'!$F$11*'Control Panel'!$B$5,0)
A13: Net Income | B13: ='P&L'!$B$11-'P&L'!$B$12 | C13: ='P&L'!$C$11-'P&L'!$C$12 | D13: ='P&L'!$D$11-'P&L'!$D$12 | E13: ='P&L'!$E$11-'P&L'!$E$12 | F13: ='P&L'!$F$11-'P&L'!$F$12

Sheet Balance Sheet
A1: Line Item (USD) | B1: Year 1 | C1: Year 2 | D1: Year 3 | E1: Year 4 | F1: Year 5
A2: Cash & Equivalents | B2: 150000 | C2: ='Balance Sheet'!$B$2+'Cash Flow'!$C$12 | D2: ='Balance Sheet'!$C$2+'Cash Flow'!$D$12 | E2: ='Balance Sheet'!$D$2+'Cash Flow'!$E$12 | F2: ='Balance Sheet'!$E$2+'Cash Flow'!$F$12
A3: Accounts Receivable | B3: =(('P&L'!$B$2+'P&L'!$B$2)/2)*'Control Panel'!$B$8/365 | C3: =(('P&L'!$C$2+'P&L'!$B$2)/2)*'Control Panel'!$B$8/365 | D3: =(('P&L'!$D$2+'P&L'!$C$2)/2)*'Control Panel'!$B$8/365 | E3: =(('P&L'!$E$2+'P&L'!$D$2)/2)*'Control Panel'!$B$8/365 | F3: =(('P&L'!$F$2+'P&L'!$E$2)/2)*'Control Panel'!$B$8/365
A4: Inventory | B4: =(('P&L'!$B$3+'P&L'!$B$3)/2)*'Control Panel'!$B$9/365 | C4: =(('P&L'!$C$3+'P&L'!$B$3)/2)*'Control Panel'!$B$9/365 | D4: =(('P&L'!$D$3+'P&L'!$C$3)/2)*'Control Panel'!$B$9/365 | E4: =(('P&L'!$E$3+'P&L'!$D$3)/2)*'Control Panel'!$B$9/365 | F4: =(('P&L'!$F$3+'P&L'!$E$3)/2)*'Control Panel'!$B$9/365
A5: PP&E, net | B5: 500000 | C5: ='Balance Sheet'!$B$5-('Cash Flow'!$C$8)-'P&L'!$C$8 | D5: ='Balance Sheet'!$C$5-('Cash Flow'!$D$8)-'P&L'!$D$8 | E5: ='Balance Sheet'!$D$5-('Cash Flow'!$E$8)-'P&L'!$E$8 | F5: ='Balance Sheet'!$E$5-('Cash Flow'!$F$8)-'P&L'!$F$8
A6: Total Assets | B6: ='Balance Sheet'!$B$2+'Balance Sheet'!$B$3+'Balance Sheet'!$B$4+'Balance Sheet'!$B$5 | C6: ='Balance Sheet'!$C$2+'Balance Sheet'!$C$3+'Balance Sheet'!$C$4+'Balance Sheet'!$C$5 | D6: ='Balance Sheet'!$D$2+'Balance Sheet'!$D$3+'Balance Sheet'!$D$4+'Balance Sheet'!$D$5 | E6: ='Balance Sheet'!$E$2+'Balance Sheet'!$E$3+'Balance Sheet'!$E$4+'Balance Sheet'!$E$5 | F6: ='Balance Sheet'!$F$2+'Balance Sheet'!$F$3+'Balance Sheet'!$F$4+'Balance Sheet'!$F$5
A7: LIABILITIES & EQUITY
A8: Accounts Payable | B8: =(('P&L'!$B$3+'P&L'!$B$3)/2)*'Control Panel'!$B$10/365 | C8: =(('P&L'!$C$3+'P&L'!$B$3)/2)*'Control Panel'!$B$10/365 | D8: =(('P&L'!$D$3+'P&L'!$C$3)/2)*'Control Panel'!$B$10/365 | E8: =(('P&L'!$E$3+'P&L'!$D$3)/2)*'Control Panel'!$B$10/365 | F8: =(('P&L'!$F$3+'P&L'!$E$3)/2)*'Control Panel'!$B$10/365
A9: Debt | B9: 200000 | C9: =MAX(0,'Balance Sheet'!$B$9-'Control Panel'!$B$12) | D9: =MAX(0,'Balance Sheet'!$C$9-'Control Panel'!$B$12) | E9: =MAX(0,'Balance Sheet'!$D$9-'Control Panel'!$B$12) | F9: =MAX(0,'Balance Sheet'!$E$9-'Control Panel'!$B$12)
A10: Paid-In Capital | B10: ='Balance Sheet'!$B$6-'Balance Sheet'!$B$8-'Balance Sheet'!$B$9-'Balance Sheet'!$B$11 | C10: ='Balance Sheet'!$B$10 | D10: ='Balance Sheet'!$B$10 | E10: ='Balance Sheet'!$B$10 | F10: ='Balance Sheet'!$B$10
A11: Retained Earnings | B11: ='P&L'!$B$13 | C11: ='Balance Sheet'!$B$11+'P&L'!$C$13 | D11: ='Balance Sheet'!$C$11+'P&L'!$D$13 | E11: ='Balance Sheet'!$D$11+'P&L'!$E$13 | F11: ='Balance Sheet'!$E$11+'P&L'!$F$13
A12: Total Liabilities & Equity | B12: ='Balance Sheet'!$B$8+'Balance Sheet'!$B$9+'Balance Sheet'!$B$10+'Balance Sheet'!$B$11 | C12: ='Balance Sheet'!$C$8+'Balance Sheet'!$C$9+'Balance Sheet'!$C$10+'Balance Sheet'!$C$11 | D12: ='Balance Sheet'!$D$8+'Balance Sheet'!$D$9+'Balance Sheet'!$D$10+'Balance Sheet'!$D$11 | E12: ='Balance Sheet'!$E$8+'Balance Sheet'!$E$9+'Balance Sheet'!$E$10+'Balance Sheet'!$E$11 | F12: ='Balance Sheet'!$F$8+'Balance Sheet'!$F$9+'Balance Sheet'!$F$10+'Balance Sheet'!$F$11
A14: Balance Check (must = 0) | B14: ='Balance Sheet'!$B$6-'Balance Sheet'!$B$12 | C14: ='Balance Sheet'!$C$6-'Balance Sheet'!$C$12 | D14: ='Balance Sheet'!$D$6-'Balance Sheet'!$D$12 | E14: ='Balance Sheet'!$E$6-'Balance Sheet'!$E$12 | F14: ='Balance Sheet'!$F$6-'Balance Sheet'!$F$12

Sheet Cash Flow
A1: Line Item (USD) | B1: Year 1 | C1: Year 2 | D1: Year 3 | E1: Year 4 | F1: Year 5
A2: Net Income | B2: ='P&L'!$B$13 | C2: ='P&L'!$C$13 | D2: ='P&L'!$D$13 | E2: ='P&L'!$E$13 | F2: ='P&L'!$F$13
A3: + Depreciation & Amortization | B3: ='P&L'!$B$8 | C3: ='P&L'!$C$8 | D3: ='P&L'!$D$8 | E3: ='P&L'!$E$8 | F3: ='P&L'!$F$8
A4: Δ Accounts Receivable | B4: =-('Balance Sheet'!$B$3-0) | C4: =-('Balance Sheet'!$C$3-'Balance Sheet'!$B$3) | D4: =-('Balance Sheet'!$D$3-'Balance Sheet'!$C$3) | E4: =-('Balance Sheet'!$E$3-'Balance Sheet'!$D$3) | F4: =-('Balance Sheet'!$F$3-'Balance Sheet'!$E$3)
A5: Δ Inventory | B5: =-('Balance Sheet'!$B$4-0) | C5: =-('Balance Sheet'!$C$4-'Balance Sheet'!$B$4) | D5: =-('Balance Sheet'!$D$4-'Balance Sheet'!$C$4) | E5: =-('Balance Sheet'!$E$4-'Balance Sheet'!$D$4) | F5: =-('Balance Sheet'!$F$4-'Balance Sheet'!$E$4)
A6: Δ Accounts Payable | B6: ='Balance Sheet'!$B$8-0 | C6: ='Balance Sheet'!$C$8-'Balance Sheet'!$B$8 | D6: ='Balance Sheet'!$D$8-'Balance Sheet'!$C$8 | E6: ='Balance Sheet'!$E$8-'Balance Sheet'!$D$8 | F6: ='Balance Sheet'!$F$8-'Balance Sheet'!$E$8
A7: Cash from Operations | B7: ='Cash Flow'!$B$2+'Cash Flow'!$B$3+'Cash Flow'!$B$4+'Cash Flow'!$B$5+'Cash Flow'!$B$6 | C7: ='Cash Flow'!$C$2+'Cash Flow'!$C$3+'Cash Flow'!$C$4+'Cash Flow'!$C$5+'Cash Flow'!$C$6 | D7: ='Cash Flow'!$D$2+'Cash Flow'!$D$3+'Cash Flow'!$D$4+'Cash Flow'!$D$5+'Cash Flow'!$D$6 | E7: ='Cash Flow'!$E$2+'Cash Flow'!$E$3+'Cash Flow'!$E$4+'Cash Flow'!$E$5+'Cash Flow'!$E$6 | F7: ='Cash Flow'!$F$2+'Cash Flow'!$F$3+'Cash Flow'!$F$4+'Cash Flow'!$F$5+'Cash Flow'!$F$6
A8: Capital Expenditures | B8: =-('P&L'!$B$2*'Control Panel'!$B$7) | C8: =-('P&L'!$C$2*'Control Panel'!$B$7) | D8: =-('P&L'!$D$2*'Control Panel'!$B$7) | E8: =-('P&L'!$E$2*'Control Panel'!$B$7) | F8: =-('P&L'!$F$2*'Control Panel'!$B$7)
A9: Cash from Investing | B9: ='Cash Flow'!$B$8 | C9: ='Cash Flow'!$C$8 | D9: ='Cash Flow'!$D$8 | E9: ='Cash Flow'!$E$8 | F9: ='Cash Flow'!$F$8
A10: Debt Repayment | B10: =-('Balance Sheet'!$B$9-200000) | C10: =-('Balance Sheet'!$C$9-'Balance Sheet'!$B$9) | D10: =-('Balance Sheet'!$D$9-'Balance Sheet'!$C$9) | E10: =-('Balance Sheet'!$E$9-'Balance Sheet'!$D$9) | F10: =-('Balance Sheet'!$F$9-'Balance Sheet'!$E$9)
A11: Cash from Financing | B11: ='Cash Flow'!$B$10 | C11: ='Cash Flow'!$C$10 | D11: ='Cash Flow'!$D$10 | E11: ='Cash Flow'!$E$10 | F11: ='Cash Flow'!$F$10
A12: Net Change in Cash | B12: ='Cash Flow'!$B$7+'Cash Flow'!$B$9+'Cash Flow'!$B$11 | C12: ='Cash Flow'!$C$7+'Cash Flow'!$C$9+'Cash Flow'!$C$11 | D12: ='Cash Flow'!$D$7+'Cash Flow'!$D$9+'Cash Flow'!$D$11 | E12: ='Cash Flow'!$E$7+'Cash Flow'!$E$9+'Cash Flow'!$E$11 | F12: ='Cash Flow'!$F$7+'Cash Flow'!$F$9+'Cash Flow'!$F$11

Sheet Valuation
A1: DCF VALUATION (USD)
A3: WACC | B3: ='Control Panel'!$B$13
A4: Perpetual Growth | B4: ='Control Panel'!$B$14
A6: Free Cash Flow to Firm (FCFF)
B7: Year 1 | C7: Year 2 | D7: Year 3 | E7: Year 4 | F7: Year 5
B8: ='P&L'!$B$9*(1-'Control Panel'!$B$5)+'P&L'!$B$8+'Cash Flow'!$B$4+'Cash Flow'!$B$5+'Cash Flow'!$B$6+'Cash Flow'!$B$8 | C8: ='P&L'!$C$9*(1-'Control Panel'!$B$5)+'P&L'!$C$8+'Cash Flow'!$C$4+'Cash Flow'!$C$5+'Cash Flow'!$C$6+'Cash Flow'!$C$8 | D8: ='P&L'!$D$9*(1-'Control Panel'!$B$5)+'P&L'!$D$8+'Cash Flow'!$D$4+'Cash Flow'!$D$5+'Cash Flow'!$D$6+'Cash Flow'!$D$8 | E8: ='P&L'!$E$9*(1-'Control Panel'!$B$5)+'P&L'!$E$8+'Cash Flow'!$E$4+'Cash Flow'!$E$5+'Cash Flow'!$E$6+'Cash Flow'!$E$8 | F8: ='P&L'!$F$9*(1-'Control Panel'!$B$5)+'P&L'!$F$8+'Cash Flow'!$F$4+'Cash Flow'!$F$5+'Cash Flow'!$F$6+'Cash Flow'!$F$8
A10: Terminal Value | B10: =IFERROR(('Valuation'!$F$8*(1+'Valuation'!$B$4))/('Valuation'!$B$3-'Valuation'!$B$4),"⚠ WACC ≤ g")
A11: Enterprise Value | B11: =IFERROR(NPV('Valuation'!$B$3,'Valuation'!$B$8:$F$8)+(B10/(1+'Valuation'!$B$3)^5),0)
A12: Less: Net Debt | B12: ='Balance Sheet'!$F$9-'Balance Sheet'!$F$2
A13: Equity Value | B13: =B11-B12
A15: Implied EV/Revenue (Yr 5) | B15: =IFERROR(B11/'P&L'!$F$2,0)
A16: Implied EV/EBITDA (Yr 5) | B16: =IFERROR(B11/'P&L'!$F$7,0)

Sheet Sensitivity
A1: Net Income Sensitivity – Year 5
A2: ▶ Select B3:H10 → Data → What-If Analysis → Data Table | Row input: 'Control Panel'!$B$24 | Col input: 'Control Panel'!$B$25
A3: ='P&L'!$F$13 | B3: 0.35 | C3: 0.4 | D3: 0.45 | E3: 0.5 | F3: 0.55 | G3: 0.6 | H3: 0.65
A4: 0.02 | B4: — | C4: — | D4: — | E4: — | F4: — | G4: — | H4: —
A5: 0.05 | B5: — | C5: — | D5: — | E5: — | F5: — | G5: — | H5: —
A6: 0.08 | B6: — | C6: — | D6: — | E6: — | F6: — | G6: — | H6: —
A7: 0.11 | B7: — | C7: — | D7: — | E7: — | F7: — | G7: — | H7: —
A8: 0.14 | B8: — | C8: — | D8: — | E8: — | F8: — | G8: — | H8: —
A9: 0.17 | B9: — | C9: — | D9: — | E9: — | F9: — | G9: — | H9: —
A10: 0.2 | B10: — | C10: — | D10: — | E10: — | F10: — | G10: — | H10: —

Sheet Insights
A1: KEY PERFORMANCE INDICATORS
A2: Metric | B2: Year 5 Value | C2: Flag / Commentary
A3: Revenue CAGR (Yr 1 → 5) | B3: =IFERROR(('P&L'!$F$2/'P&L'!$B$2)^(1/4)-1,0) | C3: =IF('Insights'!B3>0.15,"🚀 Strong","=IF"&IF('Insights'!B3>0.08,"✅ Solid","⚠ Below 8%"))
A4: EBITDA Margin | B4: =IFERROR('P&L'!$F$7/'P&L'!$F$2,0) | C4: =IF('Insights'!B4>=0.2,"✅ Healthy (≥20%)","⚠ Below 20% — watch costs")
A5: Net Income Margin | B5: =IFERROR('P&L'!$F$13/'P&L'!$F$2,0) | C5: =IF('Insights'!B5>=0.1,"✅ Solid (≥10%)","⚠ Below 10%")
A6: Gross Margin | B6: =IFERROR(1-'Control Panel'!$B$25,0) | C6: =IF(1-'Control Panel'!$B$25>=0.5,"✅ Strong (≥50%)","⚠ Below 50%")
A7: Profitable (Year 5)? | B7: =IF('P&L'!$F$13>0,"✅ Yes","❌ No")
A8: Ending Cash | B8: ='Balance Sheet'!$F$2 | C8: =IF('Balance Sheet'!$F$2>0,"✅ Positive","❌ NEGATIVE — model may be breaking")
A9: Cash Runway (years) | B9: =IFERROR(IF('Cash Flow'!$F$12<0,'Balance Sheet'!$F$2/ABS('Cash Flow'!$F$12),"∞ (positive CF)"),"N/A") | C9: Years of cash at Year 5 burn rate
A10: Break-Even Year | B10: =IFERROR(MATCH(TRUE,INDEX('P&L'!$B$13:$F$13>0,),0),"Not in forecast") | C10: First year Net Income > 0
A11: Active Scenario | B11: ='Control Panel'!$B$23 | C11: ="Base,Best,Worst available"
A12: Active Revenue Growth | B12: ='Control Panel'!$B$24 | C12: =IF('Control Panel'!$B$24>0.18,"⚠ Very aggressive","✅ Plausible")
A13: Sources & Uses Check | B13: =IFERROR('Balance Sheet'!$F$2-(150000+SUMPRODUCT(('Cash Flow'!$C$12:$F$12)*1)),0) | C13: =IF(ABS(IFERROR('Balance Sheet'!$F$2-(150000+SUMPRODUCT(('Cash Flow'!$C$12:$F$12)*1)),0))<1,"✅ Cash reconciles","❌ Cash reconciliation error")
A14: Balance Check | B14: =SUM('Balance Sheet'!$B$14:$F$14) | C14: =IF(ABS(SUM('Balance Sheet'!$B$14:$F$14))<1,"✅ Balanced","❌ Out of balance — fix Balance Sheet")

Sheet Dashboard
A1: MODEL DASHBOARD
B35: =IFERROR('P&L'!$B$7/'P&L'!$B$2,0) | C35: =IFERROR('P&L'!$C$7/'P&L'!$C$2,0) | D35: =IFERROR('P&L'!$D$7/'P&L'!$D$2,0) | E35: =IFERROR('P&L'!$E$7/'P&L'!$E$2,0) | F35: =IFERROR('P&L'!$F$7/'P&L'!$F$2,0)
